GotGit/README.md
GotGit/__init__.py
GotGit/__main__.py
GotGit/file.epub
GotGit/index.html
GotGit/css/__init__.py
GotGit/css/annotations.css
GotGit/css/main.css
GotGit/css/normalize.css
GotGit/css/popup.css
GotGit/font/__init__.py
GotGit/font/fontello.eot
GotGit/font/fontello.svg
GotGit/font/fontello.ttf
GotGit/font/fontello.woff
GotGit/img/__init__.py
GotGit/img/annotator-glyph-sprite.png
GotGit/img/annotator-icon-sprite.png
GotGit/img/apple-touch-icon.png
GotGit/img/cancelfullscreen.png
GotGit/img/close.png
GotGit/img/fullscreen.png
GotGit/img/loader.gif
GotGit/img/menu-icon.png
GotGit/img/save.png
GotGit/img/saved.png
GotGit/img/settings-s.png
GotGit/img/settings.png
GotGit/img/star.png
GotGit/js/__init__.py
GotGit/js/epub.js
GotGit/js/epub.min.js
GotGit/js/epub.min.map
GotGit/js/hooks.min.js
GotGit/js/hooks.min.map
GotGit/js/reader.js
GotGit/js/reader.js.map
GotGit/js/reader.min.js
GotGit/js/reader.min.map
GotGit/js/hooks/__init__.py
GotGit/js/hooks/extensions/__init__.py
GotGit/js/hooks/extensions/highlight.js
GotGit/js/libs/__init__.py
GotGit/js/libs/jquery.min.js
GotGit/js/libs/localforage.min.js
GotGit/js/libs/screenfull.js
GotGit/js/libs/screenfull.min.js
GotGit/js/libs/zip.min.js
GotGit/js/plugins/__init__.py
GotGit/js/plugins/hypothesis.js
GotGit/js/plugins/search.js
got_git-2024.3.1.0.dist-info/METADATA
got_git-2024.3.1.0.dist-info/WHEEL
got_git-2024.3.1.0.dist-info/entry_points.txt
got_git-2024.3.1.0.dist-info/top_level.txt
got_git-2024.3.1.0.dist-info/RECORD
